sberzvuk_api/__init__.py
sberzvuk_api/client.py
sberzvuk_api/enums.py
sberzvuk_api/errors.py
sberzvuk_api/queries.py
sberzvuk_api-1.0.2.dist-info/METADATA
sberzvuk_api-1.0.2.dist-info/WHEEL
sberzvuk_api-1.0.2.dist-info/top_level.txt
sberzvuk_api-1.0.2.dist-info/RECORD
