Metadata-Version: 2.4
Name: sberzvuk_api
Version: 1.0.2
Summary: Asynchronous wrapper for SberZvuk API
Home-page: https://github.com/Lincoln-Continental/SberZvuk_API
Author: $10,000 Lincoln Continental
License: MIT
Requires-Dist: aiohttp
Dynamic: author
Dynamic: description
Dynamic: description-content-type
Dynamic: home-page
Dynamic: license
Dynamic: requires-dist
Dynamic: summary
